wfapi/__init__.py
wfapi/__main__.py
wfapi/browser.py
wfapi/config.py
wfapi/error.py
wfapi/node.py
wfapi/operation.py
wfapi/parse.py
wfapi/project.py
wfapi/quota.py
wfapi/tools.py
wfapi/workflowy.py
wfapi-0.8.1.dist-info/DESCRIPTION.rst
wfapi-0.8.1.dist-info/METADATA
wfapi-0.8.1.dist-info/RECORD
wfapi-0.8.1.dist-info/WHEEL
wfapi-0.8.1.dist-info/metadata.json
wfapi-0.8.1.dist-info/top_level.txt
