Metadata-Version: 2.0
Name: wfapi
Version: 0.8.1
Summary: Workflowy's Unoffical API for Python 3.6
Home-page: https://github.com/ecmaxp/wfapi
Author: EcmaXp
Author-email: wfapi@ecmaxp.net
License: UNKNOWN
Keywords: workflowy
Platform: UNKNOWN
Classifier: Development Status :: 3 - Alpha
Classifier: Operating System :: OS Independent
Classifier: Programming Language :: Python
Classifier: Programming Language :: Python :: 3 :: Only
Classifier: Programming Language :: Python :: 3.6
Classifier: Topic :: Internet :: WWW/HTTP :: Dynamic Content
Requires-Python: >=3.6
